automatic/__init__.py
automatic/automatic.py
wangzhenbin-0.0.3.dist-info/LICENSE
wangzhenbin-0.0.3.dist-info/METADATA
wangzhenbin-0.0.3.dist-info/WHEEL
wangzhenbin-0.0.3.dist-info/top_level.txt
wangzhenbin-0.0.3.dist-info/RECORD
