Metadata-Version: 2.1
Name: wangzhenbin
Version: 0.0.3
Summary: Give dedicated students and teachers time reminders
Author: wangzhenbin
Author-email: 2175206532@qq.com
License-File: LICENSE
